{
  "$schema": "https://json-schema.org/draft/2020-12/schema",
  "$id": "jarvis_memory_board.v1",
  "title": "jarvis_memory_board v1",
  "type": "object",
  "required": [
    "jarvis_memory_board_version",
    "module_id",
    "cisiv_stage",
    "claim_label"
  ],
  "properties": {
    "jarvis_memory_board_version": {
      "const": "jarvis_memory_board.v1"
    },
    "module_id": {
      "type": "string",
      "minLength": 1
    },
    "status_summary": {
      "type": "string"
    },
    "cisiv_stage": {
      "enum": [
        "concept",
        "identity",
        "structure",
        "implementation",
        "verification"
      ]
    },
    "claim_label": {
      "enum": [
        "asserted",
        "proven",
        "rejected"
      ]
    },
    "read_only": {
      "type": "boolean"
    }
  },
  "additionalProperties": true
}
